redfysh_cli/__init__.py
redfysh_cli/cli.py
redfysh_cli-0.0.3.dist-info/LICENSE.txt
redfysh_cli-0.0.3.dist-info/METADATA
redfysh_cli-0.0.3.dist-info/NOTICE.txt
redfysh_cli-0.0.3.dist-info/WHEEL
redfysh_cli-0.0.3.dist-info/entry_points.txt
redfysh_cli-0.0.3.dist-info/top_level.txt
redfysh_cli-0.0.3.dist-info/RECORD
